<?xml version='1.0' encoding='utf-8' standalone='yes' ?>
<Data>
<Color_Temp>
2562,2668,2777,2922,3056,3206,3353,3522,3688,3863,4070,4268,4474,4713,4978,5224,5518,5809,5984,6214,6439,6743,7116,7476,7879,8056,8319,8612,8896,9226,9627,9876
</Color_Temp>
<Red>
1000,1000,1000,1000,1000,1000,1000,1000,1000,1000,1000,1000,1000,1000,1000,1000,1000,1000,1000,1000,1000,1000,1000,1000,1000,985,970,955,940,925,910,899
</Red>
<Green>
590,610,630,650,670,690,710,730,750,770,790,810,830,850,870,890,910,930,940,950,960,970,980,990,1000,990,980,970,960,950,940,935
</Green>
<Blue>
255,280,305,330,355,385,415,450,485,520,555,590,625,660,700,735,775,810,830,855,880,910,940,970,1000,1000,1000,1000,1000,1000,1000,1000
</Blue>
<Default>
    7879
</Default>
</Data>